{"trial_id": "23", "hyperparameters": {"space": [{"class_name": "Int", "config": {"name": "numLayers", "default": null, "conditions": [], "min_value": 2, "max_value": 5, "step": 1, "sampling": "linear"}}, {"class_name": "Int", "config": {"name": "nodes_0", "default": null, "conditions": [], "min_value": 24, "max_value": 192, "step": 24, "sampling": "linear"}}, {"class_name": "Int", "config": {"name": "nodes_1", "default": null, "conditions": [], "min_value": 24, "max_value": 192, "step": 24, "sampling": "linear"}}, {"class_name": "Float", "config": {"name": "learningRate", "default": 0.0001, "conditions": [], "min_value": 0.0001, "max_value": 0.01, "step": null, "sampling": "log"}}, {"class_name": "Int", "config": {"name": "nodes_2", "default": null, "conditions": [], "min_value": 24, "max_value": 192, "step": 24, "sampling": "linear"}}, {"class_name": "Int", "config": {"name": "nodes_3", "default": null, "conditions": [], "min_value": 24, "max_value": 192, "step": 24, "sampling": "linear"}}, {"class_name": "Int", "config": {"name": "nodes_4", "default": null, "conditions": [], "min_value": 24, "max_value": 192, "step": 24, "sampling": "linear"}}], "values": {"numLayers": 4, "nodes_0": 168, "nodes_1": 144, "learningRate": 0.00134650033602513, "nodes_2": 48, "nodes_3": 96, "nodes_4": 24}}, "metrics": {"metrics": {"accuracy": {"direction": "max", "observations": [{"value": [0.4987024664878845], "step": 5}]}, "loss": {"direction": "min", "observations": [{"value": [0.6931769847869873], "step": 5}]}, "val_accuracy": {"direction": "max", "observations": [{"value": [0.502774178981781], "step": 5}]}, "val_loss": {"direction": "min", "observations": [{"value": [0.6931347846984863], "step": 5}]}}}, "score": 0.502774178981781, "best_step": 5, "status": "COMPLETED", "message": null}